razorback/__init__.py
razorback/_version.py
razorback/calibrations.py
razorback/cli.py
razorback/data.py
razorback/errors.py
razorback/fourier_transform.py
razorback/mestimator.py
razorback/prefilters.py
razorback/signalset.py
razorback/utils.py
razorback/weights.py
razorback/io/__init__.py
razorback/io/ats.py
razorback/io/binary_file_array.py
razorback-0.4.3.dist-info/AUTHORS
razorback-0.4.3.dist-info/LICENSE
razorback-0.4.3.dist-info/METADATA
razorback-0.4.3.dist-info/WHEEL
razorback-0.4.3.dist-info/entry_points.txt
razorback-0.4.3.dist-info/top_level.txt
razorback-0.4.3.dist-info/RECORD
