Metadata-Version: 2.1
Name: razorback
Version: 0.4.3
Summary: Robust estimation of linear response functions
Author-email: Farid Smai <f.smai@brgm.fr>
License: GNU GPLv3 License
Project-URL: Homepage, https://github.com/BRGM/razorback
Project-URL: Documentation, https://razorback.readthedocs.io
Project-URL: Source, https://github.com/BRGM/razorback
Classifier: License :: OSI Approved :: GNU General Public License v3 (GPLv3)
Classifier: Programming Language :: Python :: 3
Requires-Python: >=3.6
License-File: LICENSE
License-File: AUTHORS
Requires-Dist: numpy
Requires-Dist: scipy
Requires-Dist: dask[array]
Requires-Dist: click
